.gitignore
MANIFEST.in
setup.py
ebs/__init__.py
ebs/linuxnode/__init__.py
ebs/linuxnode/exim/__init__.py
ebs/linuxnode/exim/local.py
ebs/linuxnode/exim/mixin.py
ebs/linuxnode/gui/__init__.py
ebs/linuxnode/gui/kivy/__init__.py
ebs/linuxnode/gui/kivy/exim/__init__.py
ebs/linuxnode/gui/kivy/exim/indicator.py
ebs/linuxnode/gui/kivy/exim/mixin.py
ebs/linuxnode/gui/kivy/exim/images/done.png
ebs/linuxnode/gui/kivy/exim/images/download.png
ebs/linuxnode/gui/kivy/exim/images/upload.png
ebs/linuxnode/gui/kivy/exim/images/usbdrive.png
ebs_linuxnode_exim.egg-info/PKG-INFO
ebs_linuxnode_exim.egg-info/SOURCES.txt
ebs_linuxnode_exim.egg-info/dependency_links.txt
ebs_linuxnode_exim.egg-info/requires.txt
ebs_linuxnode_exim.egg-info/top_level.txt
example/app.py
example/node.py
example/run.py
example/run_headless.py