Metadata-Version: 2.1
Name: ebs-linuxnode-exim
Version: 3.1.0
Summary: Export Import Infrastructure for EBS Linuxnode Applications
Home-page: https://github.com/ebs-universe/ebs-linuxnode-exim
Author: Chintalagiri Shashank
Author-email: shashank.chintalagiri@gmail.com
Classifier: Development Status :: 5 - Production/Stable
Classifier: Intended Audience :: Developers
Classifier: License :: OSI Approved :: GNU General Public License v3 or later (GPLv3+)
Classifier: Programming Language :: Python
Classifier: Programming Language :: Python :: 3
Classifier: Programming Language :: Python :: 3.6
Classifier: Operating System :: POSIX :: Linux
Requires-Dist: six
Requires-Dist: setuptools-scm
Requires-Dist: ebs-linuxnode-core
Requires-Dist: appdirs
